greptimedb_mcp_server/__init__.py
greptimedb_mcp_server/config.py
greptimedb_mcp_server/server.py
greptimedb_mcp_server/utils.py
greptimedb_mcp_server/templates/metrics_analysis/config.yaml
greptimedb_mcp_server/templates/metrics_analysis/template.md
greptimedb_mcp_server/templates/table_operation/config.yaml
greptimedb_mcp_server/templates/table_operation/template.md
mseep_greptimedb_mcp_server-0.2.3.dist-info/METADATA
mseep_greptimedb_mcp_server-0.2.3.dist-info/WHEEL
mseep_greptimedb_mcp_server-0.2.3.dist-info/entry_points.txt
mseep_greptimedb_mcp_server-0.2.3.dist-info/licenses/LICENSE.md
mseep_greptimedb_mcp_server-0.2.3.dist-info/RECORD
